olga/__init__.py
olga/compute_pgen.py
olga/generate_sequences.py
olga/generation_probability.py
olga/load_model.py
olga/preprocess_generative_model_and_data.py
olga/sequence_generation.py
olga/utils.py
olga/default_models/.DS_Store
olga/default_models/human_B_heavy/J_gene_CDR3_anchors.csv
olga/default_models/human_B_heavy/V_gene_CDR3_anchors.csv
olga/default_models/human_B_heavy/model_marginals.txt
olga/default_models/human_B_heavy/model_params.txt
olga/default_models/human_B_kappa/J_gene_CDR3_anchors.csv
olga/default_models/human_B_kappa/V_gene_CDR3_anchors.csv
olga/default_models/human_B_kappa/model_marginals.txt
olga/default_models/human_B_kappa/model_params.txt
olga/default_models/human_B_lambda/.DS_Store
olga/default_models/human_B_lambda/J_gene_CDR3_anchors.csv
olga/default_models/human_B_lambda/V_gene_CDR3_anchors.csv
olga/default_models/human_B_lambda/model_marginals.txt
olga/default_models/human_B_lambda/model_params.txt
olga/default_models/human_T_alpha/J_gene_CDR3_anchors.csv
olga/default_models/human_T_alpha/V_gene_CDR3_anchors.csv
olga/default_models/human_T_alpha/model_marginals.txt
olga/default_models/human_T_alpha/model_params.txt
olga/default_models/human_T_beta/J_gene_CDR3_anchors.csv
olga/default_models/human_T_beta/V_gene_CDR3_anchors.csv
olga/default_models/human_T_beta/model_marginals.txt
olga/default_models/human_T_beta/model_params.txt
olga/default_models/mouse_T_alpha/J_gene_CDR3_anchors.csv
olga/default_models/mouse_T_alpha/V_gene_CDR3_anchors.csv
olga/default_models/mouse_T_alpha/model_marginals.txt
olga/default_models/mouse_T_alpha/model_params.txt
olga/default_models/mouse_T_beta/J_gene_CDR3_anchors.csv
olga/default_models/mouse_T_beta/V_gene_CDR3_anchors.csv
olga/default_models/mouse_T_beta/model_marginals.txt
olga/default_models/mouse_T_beta/model_params.txt
olga-1.2.4.data/data/LICENSE
olga-1.2.4.data/data/README.md
olga-1.2.4.data/data/example_expanded_amino_acid_alphabet.txt
olga-1.2.4.dist-info/LICENSE
olga-1.2.4.dist-info/METADATA
olga-1.2.4.dist-info/WHEEL
olga-1.2.4.dist-info/entry_points.txt
olga-1.2.4.dist-info/top_level.txt
olga-1.2.4.dist-info/RECORD
